{
  "@microsoft/generator-sharepoint": {
    "plusBeta": false,
    "isCreatingSolution": true,
    "nodeVersion": "18.19.0",
    "sdksVersions": {
      "@microsoft/microsoft-graph-client": "3.0.2",
      "@microsoft/teams-js": "2.12.0"
    },
    "version": "1.18.2",
    "libraryName": "mail-app",
    "libraryId": "0e1a960f-683d-442f-8a26-a413573ed228",
    "environment": "spo",
    "packageManager": "npm",
    "solutionName": "mail-app",
    "solutionShortDescription": "mail-app description",
    "skipFeatureDeployment": true,
    "isDomainIsolated": false,
    "componentType": "webpart"
  }
}
